Metadata-Version: 1.0
Name: hmp-basic-matrix-algebra
Version: 1.2
Summary: Basic Matrix Algebra Operations
Home-page: UNKNOWN
Author: Henrique M. Prado
Author-email: hmartins.prado@gmail.com
License: UNKNOWN
Platform: UNKNOWN
